pm4pybpmn/__init__.py
pm4pybpmn/objects/__init__.py
pm4pybpmn/objects/bpmn/__init__.py
pm4pybpmn/objects/bpmn/exporter/__init__.py
pm4pybpmn/objects/bpmn/exporter/bpmn20.py
pm4pybpmn/objects/bpmn/exporter/bpmn_diagram_export.py
pm4pybpmn/objects/bpmn/importer/__init__.py
pm4pybpmn/objects/bpmn/importer/bpmn20.py
pm4pybpmn/objects/bpmn/importer/bpmn_diagram_import.py
pm4pybpmn/objects/bpmn/importer/bpmn_diagram_rep.py
pm4pybpmn/objects/bpmn/importer/bpmn_python_consts.py
pm4pybpmn/objects/bpmn/util/__init__.py
pm4pybpmn/objects/bpmn/util/bpmn_diagram_layouter.py
pm4pybpmn/objects/bpmn/util/gateway_map.py
pm4pybpmn/objects/bpmn/util/log_matching.py
pm4pybpmn/objects/conversion/__init__.py
pm4pybpmn/objects/conversion/bpmn_to_petri/__init__.py
pm4pybpmn/objects/conversion/bpmn_to_petri/factory.py
pm4pybpmn/objects/conversion/bpmn_to_petri/versions/__init__.py
pm4pybpmn/objects/conversion/bpmn_to_petri/versions/classic.py
pm4pybpmn/objects/conversion/petri_to_bpmn/__init__.py
pm4pybpmn/objects/conversion/petri_to_bpmn/factory.py
pm4pybpmn/objects/conversion/petri_to_bpmn/util/__init__.py
pm4pybpmn/objects/conversion/petri_to_bpmn/util/constants.py
pm4pybpmn/objects/conversion/petri_to_bpmn/versions/__init__.py
pm4pybpmn/objects/conversion/petri_to_bpmn/versions/classic.py
pm4pybpmn/visualization/__init__.py
pm4pybpmn/visualization/bpmn/__init__.py
pm4pybpmn/visualization/bpmn/factory.py
pm4pybpmn/visualization/bpmn/util/__init__.py
pm4pybpmn/visualization/bpmn/util/bpmn_embedding.py
pm4pybpmn/visualization/bpmn/util/bpmn_to_figure.py
pm4pybpmn/visualization/bpmn/util/convert_performance_map.py
pm4pybpmn/visualization/bpmn/util/save_view.py
pm4pybpmn/visualization/bpmn/versions/__init__.py
pm4pybpmn/visualization/bpmn/versions/alignments.py
pm4pybpmn/visualization/bpmn/versions/frequency.py
pm4pybpmn/visualization/bpmn/versions/performance.py
pm4pybpmn/visualization/bpmn/versions/wo_decoration.py
pm4pybpmn-0.1.6.dist-info/LICENSE
pm4pybpmn-0.1.6.dist-info/METADATA
pm4pybpmn-0.1.6.dist-info/WHEEL
pm4pybpmn-0.1.6.dist-info/top_level.txt
pm4pybpmn-0.1.6.dist-info/RECORD
