Metadata-Version: 2.1
Name: pm4pybpmn
Version: 0.1.6
Summary: Process Mining for Python - BPMN support
Home-page: http://www.pm4py.org
Author: PADS
Author-email: pm4py@pads.rwth-aachen.de
License: GPL 3.0
Project-URL: Documentation, http://pm4py.pads.rwth-aachen.de/documentation/
Project-URL: Source, https://github.com/pm4py/pm4py-source
Project-URL: Tracker, https://github.com/pm4py/pm4py-source/issues
Platform: UNKNOWN
Requires-Dist: pm4py
Requires-Dist: networkx (>=2.2)
Requires-Dist: bpmn-python (==0.0.18)
Requires-Dist: intervaltree
Requires-Dist: lime
Requires-Dist: joblib
Requires-Dist: pydotplus
